stax_module_sdk/Stax.py
stax_module_sdk/__init__.py
stax_module_sdk/helpers.py
stax_module_sdk/pytext.py
stax_module_sdk/wrapper.py
stax_module_sdk-0.1.8.data/scripts/stax_module_cli
stax_module_sdk-0.1.8.dist-info/LICENSE.md
stax_module_sdk-0.1.8.dist-info/METADATA
stax_module_sdk-0.1.8.dist-info/WHEEL
stax_module_sdk-0.1.8.dist-info/top_level.txt
stax_module_sdk-0.1.8.dist-info/RECORD
