Metadata-Version: 2.1
Name: stax-module-sdk
Version: 0.1.8
Summary: Stax.ai Module SDK
Home-page: https://bitbucket.org/pinetree-ai/stax-module-sdk-py/src/master/
Author: Stax.ai, Inc. <https://stax.ai>
Author-email: naru@stax.ai
License: CC-BY-NC 4.0
Platform: UNKNOWN
Classifier: Programming Language :: Python :: 3
Classifier: Operating System :: OS Independent
Requires-Python: >=3.6
License-File: LICENSE.md
Requires-Dist: retry-requests
